mosaic/__init__.py
mosaic/cli.py
mosaic/exceptions.py
mosaic/migrations.py
mosaic/models.py
mosaic/orm.py
mosaic/utils.py
mosaicdb-0.1.1.dist-info/licenses/LICENSE
mosaicdb-0.1.1.dist-info/METADATA
mosaicdb-0.1.1.dist-info/WHEEL
mosaicdb-0.1.1.dist-info/entry_points.txt
mosaicdb-0.1.1.dist-info/top_level.txt
mosaicdb-0.1.1.dist-info/RECORD
