Metadata-Version: 2.4
Name: mosaicdb
Version: 0.1.1
Summary: Universal, framework-independent ORM for Python.
Home-page: https://github.com/Akash-nath29/mosaic
Author: Akash Nath
Author-email: anath5440@gmail.com
License: MIT
Keywords: orm database sql nosql sqlite mysql postgres mongodb
Classifier: Programming Language :: Python :: 3
Classifier: License :: OSI Approved :: MIT License
Classifier: Operating System :: OS Independent
Classifier: Intended Audience :: Developers
Classifier: Topic :: Database
Classifier: Topic :: Software Development :: Libraries :: Python Modules
Requires-Python: >=3.7
License-File: LICENSE
Requires-Dist: pydantic
Requires-Dist: mysql-connector-python
Requires-Dist: psycopg2
Requires-Dist: pymongo
Dynamic: author
Dynamic: author-email
Dynamic: classifier
Dynamic: description
Dynamic: description-content-type
Dynamic: home-page
Dynamic: keywords
Dynamic: license
Dynamic: license-file
Dynamic: requires-dist
Dynamic: requires-python
Dynamic: summary
